python_rds_ref/__init__.py
python_rds_ref/dataserver.py
python_rds_ref/version.py
python_rds_ref-0.1.2.dist-info/entry_points.txt
python_rds_ref-0.1.2.dist-info/WHEEL
python_rds_ref-0.1.2.dist-info/METADATA
python_rds_ref-0.1.2.dist-info/RECORD
