Metadata-Version: 2.1
Name: python-rds-ref
Version: 0.1.2
Summary: 
Author: Hamada Gasmallah
Author-email: hamada@distributive.network
Requires-Python: >=3.8,<4.0
Classifier: Programming Language :: Python :: 3
Classifier: Programming Language :: Python :: 3.8
Classifier: Programming Language :: Python :: 3.9
Classifier: Programming Language :: Python :: 3.10
